pyquocca/__init__.py
pyquocca/envvars.py
pyquocca/flags.py
pyquocca/gunicorn.py
pyquocca/header_utils.py
pyquocca/logging.py
pyquocca/mysql.py
pyquocca/postgres.py
pyquocca/py.typed
pyquocca/xssbot.py
pyquocca-0.4.0.dist-info/METADATA
pyquocca-0.4.0.dist-info/WHEEL
pyquocca-0.4.0.dist-info/RECORD
