Metadata-Version: 2.4
Name: pyquocca
Version: 0.4.0
Summary: Challenge utilities for SecEDU CTFs (primarily UNSW's COMP6[48]43).
Author-email: Hamish Cox <hamish.cox@unsw.edu.au>
Maintainer-email: Hamish Cox <hamish.cox@unsw.edu.au>
Requires-Python: >=3.9
Requires-Dist: cryptography>=42.0.5
Requires-Dist: flask<4,>=2.0.3
Requires-Dist: gunicorn>=21.2.0
Requires-Dist: python-json-logger>=3.2.1
Requires-Dist: requests>=2.31.0
Requires-Dist: typing-extensions>=4.10.0
Provides-Extra: mysql
Requires-Dist: pymysql>=1.0.2; extra == 'mysql'
Provides-Extra: postgres
Requires-Dist: psycopg-binary>=3.2.4; extra == 'postgres'
Requires-Dist: psycopg[pool]>=3.2.4; extra == 'postgres'
